ECGfeaturizer/__init__.py
ECGfeaturizer/featurize.py
tests/__init__.py
ECG_featurizer-1.0.7.dist-info/LICENSE
ECG_featurizer-1.0.7.dist-info/METADATA
ECG_featurizer-1.0.7.dist-info/WHEEL
ECG_featurizer-1.0.7.dist-info/top_level.txt
ECG_featurizer-1.0.7.dist-info/RECORD
