Metadata-Version: 2.1
Name: ECG-featurizer
Version: 1.0.7
Summary: This Python package recognize patterns in an ECG and extract features
Home-page: https://github.com/ECG-featurizer/ECG-featurizer
Author: Bjørn-Jostein Singstad
Author-email: bjorn_sing@hotmail.com
License: UNKNOWN
Platform: UNKNOWN
Classifier: Programming Language :: Python :: 3
Classifier: License :: OSI Approved :: GNU General Public License v3 (GPLv3)
Classifier: Operating System :: OS Independent
Requires-Python: >=3.6
Requires-Dist: neurokit2 (>=0.0.41)
Requires-Dist: numpy (>=1.19.0)
Requires-Dist: wfdb (>=3.1.1)
Requires-Dist: pandas (>=1.0.5)
